xxp/__init__.py
xxp/__main__.py
xxp/_ref.py
xxp/xxp.py
xxp-22.3a1.dist-info/LICENSE.md
xxp-22.3a1.dist-info/WHEEL
xxp-22.3a1.dist-info/METADATA
xxp-22.3a1.dist-info/RECORD
