Metadata-Version: 2.1
Name: xxp
Version: 22.3a1
Summary: xxd ripoff
Home-page: https://github.com/nicktimko/xxd
License: MIT
Keywords: binary,hexdump
Author: Nick Timkovich
Author-email: prometheus235@gmail.com
Requires-Python: >=3.7,<4.0
Classifier: License :: OSI Approved :: MIT License
Classifier: Programming Language :: Python :: 3
Classifier: Programming Language :: Python :: 3.10
Classifier: Programming Language :: Python :: 3.7
Classifier: Programming Language :: Python :: 3.8
Classifier: Programming Language :: Python :: 3.9
Project-URL: Repository, https://github.com/nicktimko/xxd
